darwin_handlers/__init__.py
darwin_handlers/common/__init__.py
darwin_handlers/common/accessor.py
darwin_handlers/common/addict_comp.py
darwin_handlers/common/addict_manager.py
darwin_handlers/common/addict_pipeline.py
darwin_handlers/common/component.py
darwin_handlers/common/creation.py
darwin_handlers/common/injectable.py
darwin_handlers/common/pipeline.py
darwin_handlers/components/__init__.py
darwin_handlers/components/portfolio.py
darwin_handlers/components/requirements.py
darwin_handlers/components/backtest/__init__.py
darwin_handlers/components/backtest/load.py
darwin_handlers/components/backtest/remove.py
darwin_handlers/components/backtest/save.py
darwin_handlers/components/strategy/__init__.py
darwin_handlers/components/strategy/check.py
darwin_handlers/components/strategy/decide_strategy.py
darwin_handlers/components/strategy/find_strategy.py
darwin_handlers/components/strategy/pull_strategy.py
darwin_handlers/components/universe/__init__.py
darwin_handlers/components/universe/pull_info.py
darwin_handlers/components/universe/pull_universe.py
darwin_handlers/components/universe/verify_universe.py
darwin_handlers/data/__init__.py
darwin_handlers/data/stochastic_generator.py
darwin_handlers/environments/__init__.py
darwin_handlers/environments/backtest_env.py
darwin_handlers/environments/reinforcement.py
darwin_handlers/handlers/__init__.py
darwin_handlers/handlers/allocation.py
darwin_handlers/handlers/exchange.py
darwin_handlers/handlers/requirements.py
darwin_handlers/handlers/statespace.py
darwin_handlers/handlers/user.py
darwin_handlers/handlers/abstracts/__init__.py
darwin_handlers/handlers/abstracts/strategy.py
darwin_handlers/handlers/files/__init__.py
darwin_handlers/handlers/files/models/__init__.py
darwin_handlers/handlers/ordering/__init__.py
darwin_handlers/handlers/ordering/broker.py
darwin_handlers/handlers/ordering/order.py
darwin_handlers/handlers/strategy/__init__.py
darwin_handlers/handlers/strategy/core.py
see137-0.0.6.dist-info/METADATA
see137-0.0.6.dist-info/WHEEL
see137-0.0.6.dist-info/top_level.txt
see137-0.0.6.dist-info/RECORD
