Metadata-Version: 2.1
Name: see137
Version: 0.0.6
Summary: Hiding in plain sight
Home-page: UNKNOWN
Author: Kevin Hill
Author-email: kah.kevin.hill@gmail.com
License: UNKNOWN
Platform: UNKNOWN
Classifier: Programming Language :: Python :: 3
Classifier: License :: OSI Approved :: MIT License
Classifier: Operating System :: OS Independent
Requires-Dist: jamboree
Requires-Dist: pydantic
Requires-Dist: dask
Requires-Dist: addict
Requires-Dist: PyPortfolioOpt
Requires-Dist: faker
Requires-Dist: toolz
Requires-Dist: cytoolz
